opentelemetry/py.typed
opentelemetry/resourcedetector/gcp_resource_detector/__init__.py
opentelemetry/resourcedetector/gcp_resource_detector/_constants.py
opentelemetry/resourcedetector/gcp_resource_detector/_detector.py
opentelemetry/resourcedetector/gcp_resource_detector/_faas.py
opentelemetry/resourcedetector/gcp_resource_detector/_gae.py
opentelemetry/resourcedetector/gcp_resource_detector/_gce.py
opentelemetry/resourcedetector/gcp_resource_detector/_gke.py
opentelemetry/resourcedetector/gcp_resource_detector/_mapping.py
opentelemetry/resourcedetector/gcp_resource_detector/_metadata.py
opentelemetry/resourcedetector/gcp_resource_detector/version.py
opentelemetry_resourcedetector_gcp-1.8.0a0.dist-info/LICENSE
opentelemetry_resourcedetector_gcp-1.8.0a0.dist-info/METADATA
opentelemetry_resourcedetector_gcp-1.8.0a0.dist-info/WHEEL
opentelemetry_resourcedetector_gcp-1.8.0a0.dist-info/top_level.txt
opentelemetry_resourcedetector_gcp-1.8.0a0.dist-info/RECORD
